pythonConsoleConfigs/__init__.py
pythonConsoleConfigs/main.py
pythonConsoleConfigs/Font/Colors.py
pythonConsoleConfigs/Font/Highlights.py
pythonConsoleConfigs/Font/Styles.py
pythonConsoleConfigs/Font/__init__.py
pythonConsoleConfigs/Loading/Boxes.py
pythonConsoleConfigs/Loading/Percentages.py
pythonConsoleConfigs/Loading/__init__.py
pythonConsoleConfigs/Loading/helper.py
pythonConsoleConfigs-0.9.4.dist-info/LICENSE.md
pythonConsoleConfigs-0.9.4.dist-info/METADATA
pythonConsoleConfigs-0.9.4.dist-info/WHEEL
pythonConsoleConfigs-0.9.4.dist-info/top_level.txt
pythonConsoleConfigs-0.9.4.dist-info/RECORD
