Metadata-Version: 2.1
Name: pythonConsoleConfigs
Version: 0.9.4
Summary: Python Console Configuration
Home-page: https://github.com/StefanosGregory/PythonConsoleConfig
Author: Stefanos Grigori
Author-email: gregorystefanos@gmail.com
License: Apache License
Keywords: Python,Console,Configuration,Font,Color,Highlight,Style,Loading,Load
License-File: LICENSE.md
